[
  {
    "batch": 203,
    "status": 400,
    "mensagem": "{\"code\":\"23502\",\"details\":\"Failing row contains (fc0b5bb5-faf8-4b43-bee8-2127645a8d17, 2026-02-01, 000007387 - FERRAGEM MACAGNAN LUSSANI FILHOS LTDA - Material de ..., Geral, -28762.9, 04. SG&A, Real,"
  },
  {
    "batch": 204,
    "status": 400,
    "mensagem": "{\"code\":\"23502\",\"details\":\"Failing row contains (79794594-83cd-4066-bef5-277375c67b30, 2026-02-01, 000007387 - FERRAGEM MACAGNAN LUSSANI FILHOS LTDA - Material de ..., Geral, -28762.9, 04. SG&A, Real,"
  },
  {
    "batch": 205,
    "status": 400,
    "mensagem": "{\"code\":\"23502\",\"details\":\"Failing row contains (a75698f4-5737-4845-9d7d-390f6261cd2d, 2026-02-01, 000007387 - FERRAGEM MACAGNAN LUSSANI FILHOS LTDA - Material de ..., Geral, -28762.9, 04. SG&A, Real,"
  },
  {
    "batch": 206,
    "status": 400,
    "mensagem": "{\"code\":\"23502\",\"details\":\"Failing row contains (f786678e-1186-4392-882a-65c7fe163014, 2026-02-01, 000007387 - FERRAGEM MACAGNAN LUSSANI FILHOS LTDA - Material de ..., Geral, -28762.9, 04. SG&A, Real,"
  },
  {
    "batch": 207,
    "status": 400,
    "mensagem": "{\"code\":\"23502\",\"details\":\"Failing row contains (1cdb53fc-2deb-4b7b-b45c-8d04683aa2b2, 2026-02-01, 000007387 - FERRAGEM MACAGNAN LUSSANI FILHOS LTDA - Material de ..., Geral, -28762.9, 04. SG&A, Real,"
  },
  {
    "batch": 208,
    "status": 400,
    "mensagem": "{\"code\":\"23502\",\"details\":\"Failing row contains (78a72fa8-16c4-4a80-b68a-508c81232575, 2026-02-01, 000007387 - FERRAGEM MACAGNAN LUSSANI FILHOS LTDA - Material de ..., Geral, -28762.9, 04. SG&A, Real,"
  },
  {
    "batch": 209,
    "status": 400,
    "mensagem": "{\"code\":\"23502\",\"details\":\"Failing row contains (73c083b3-478e-4631-a3a6-f9f11995694c, 2026-02-01, 000007387 - FERRAGEM MACAGNAN LUSSANI FILHOS LTDA - Material de ..., Geral, -28762.9, 04. SG&A, Real,"
  },
  {
    "batch": 210,
    "status": 400,
    "mensagem": "{\"code\":\"23502\",\"details\":\"Failing row contains (185bb22a-90c3-4ff8-bcd0-1836803cc20c, 2026-02-01, 000007387 - FERRAGEM MACAGNAN LUSSANI FILHOS LTDA - Material de ..., Geral, -28762.9, 04. SG&A, Real,"
  },
  {
    "batch": 211,
    "status": 400,
    "mensagem": "{\"code\":\"23502\",\"details\":\"Failing row contains (f16e45e1-a257-4472-bd3c-9ba03b386e13, 2026-02-01, 000007387 - FERRAGEM MACAGNAN LUSSANI FILHOS LTDA - Material de ..., Geral, -28762.9, 04. SG&A, Real,"
  },
  {
    "batch": 212,
    "status": 400,
    "mensagem": "{\"code\":\"23502\",\"details\":\"Failing row contains (1545aa39-7383-4076-b735-c64c212b628e, 2026-02-01, 000007387 - FERRAGEM MACAGNAN LUSSANI FILHOS LTDA - Material de ..., Geral, -28762.9, 04. SG&A, Real,"
  },
  {
    "batch": 213,
    "status": 400,
    "mensagem": "{\"code\":\"23502\",\"details\":\"Failing row contains (4db15464-aa71-4318-b4c3-b88c009d560b, 2026-02-01, 000007387 - FERRAGEM MACAGNAN LUSSANI FILHOS LTDA - Material de ..., Geral, -28762.9, 04. SG&A, Real,"
  },
  {
    "batch": 214,
    "status": 400,
    "mensagem": "{\"code\":\"23502\",\"details\":\"Failing row contains (d2d238ab-9014-4242-9c5e-1743d2ed5717, 2026-02-01, 000007387 - FERRAGEM MACAGNAN LUSSANI FILHOS LTDA - Material de ..., Geral, -28762.9, 04. SG&A, Real,"
  },
  {
    "batch": 215,
    "status": 400,
    "mensagem": "{\"code\":\"23502\",\"details\":\"Failing row contains (0c1636f4-4a9d-49ef-95de-3e20731397d1, 2026-02-01, 000007387 - FERRAGEM MACAGNAN LUSSANI FILHOS LTDA - Material de ..., Geral, -28762.9, 04. SG&A, Real,"
  },
  {
    "batch": 216,
    "status": 400,
    "mensagem": "{\"code\":\"23502\",\"details\":\"Failing row contains (674b3844-deae-44d6-954c-2dddd82e632d, 2026-02-01, 000007387 - FERRAGEM MACAGNAN LUSSANI FILHOS LTDA - Material de ..., Geral, -28762.9, 04. SG&A, Real,"
  },
  {
    "batch": 217,
    "status": 400,
    "mensagem": "{\"code\":\"23502\",\"details\":\"Failing row contains (b8c7b19e-8a58-487c-8df0-8b32fa892983, 2026-02-01, 000007387 - FERRAGEM MACAGNAN LUSSANI FILHOS LTDA - Material de ..., Geral, -28762.9, 04. SG&A, Real,"
  },
  {
    "batch": 218,
    "status": 400,
    "mensagem": "{\"code\":\"23502\",\"details\":\"Failing row contains (dcd3d611-3e92-4db6-aabf-897a028e841d, 2026-02-01, 000007387 - FERRAGEM MACAGNAN LUSSANI FILHOS LTDA - Material de ..., Geral, -28762.9, 04. SG&A, Real,"
  },
  {
    "batch": 219,
    "status": 400,
    "mensagem": "{\"code\":\"23502\",\"details\":\"Failing row contains (8cbe2a6d-4329-4935-9503-d6bf220d11d8, 2026-02-01, 000007387 - FERRAGEM MACAGNAN LUSSANI FILHOS LTDA - Material de ..., Geral, -28762.9, 04. SG&A, Real,"
  },
  {
    "batch": 220,
    "status": 400,
    "mensagem": "{\"code\":\"23502\",\"details\":\"Failing row contains (f2f97d46-0477-43ed-84ea-762ec8adb532, 2026-02-01, 000007387 - FERRAGEM MACAGNAN LUSSANI FILHOS LTDA - Material de ..., Geral, -28762.9, 04. SG&A, Real,"
  },
  {
    "batch": 221,
    "status": 400,
    "mensagem": "{\"code\":\"23502\",\"details\":\"Failing row contains (4696f2b2-41c9-4f61-b6ca-d8a2f235da86, 2026-02-01, 000007387 - FERRAGEM MACAGNAN LUSSANI FILHOS LTDA - Material de ..., Geral, -28762.9, 04. SG&A, Real,"
  },
  {
    "batch": 222,
    "status": 400,
    "mensagem": "{\"code\":\"23502\",\"details\":\"Failing row contains (35022025-bc4d-4d5c-ae59-0b49ea072ce1, 2026-02-01, 000007387 - FERRAGEM MACAGNAN LUSSANI FILHOS LTDA - Material de ..., Geral, -28762.9, 04. SG&A, Real,"
  },
  {
    "batch": 223,
    "status": 400,
    "mensagem": "{\"code\":\"23502\",\"details\":\"Failing row contains (f30d2454-f0b8-4132-b28b-31069eaea932, 2026-02-01, 000007387 - FERRAGEM MACAGNAN LUSSANI FILHOS LTDA - Material de ..., Geral, -28762.9, 04. SG&A, Real,"
  },
  {
    "batch": 224,
    "status": 400,
    "mensagem": "{\"code\":\"23502\",\"details\":\"Failing row contains (39eb815c-9463-4777-952e-8e71e999713f, 2026-02-01, 000007387 - FERRAGEM MACAGNAN LUSSANI FILHOS LTDA - Material de ..., Geral, -28762.9, 04. SG&A, Real,"
  },
  {
    "batch": 225,
    "status": 400,
    "mensagem": "{\"code\":\"23502\",\"details\":\"Failing row contains (3b7452f7-b348-4ecc-9b21-717c09f3f461, 2026-02-01, 000007387 - FERRAGEM MACAGNAN LUSSANI FILHOS LTDA - Material de ..., Geral, -28762.9, 04. SG&A, Real,"
  },
  {
    "batch": 226,
    "status": 400,
    "mensagem": "{\"code\":\"23502\",\"details\":\"Failing row contains (abb73eb9-b461-47cc-ab08-2b27a5a004cd, 2026-02-01, 000007387 - FERRAGEM MACAGNAN LUSSANI FILHOS LTDA - Material de ..., Geral, -28762.9, 04. SG&A, Real,"
  },
  {
    "batch": 227,
    "status": 400,
    "mensagem": "{\"code\":\"23502\",\"details\":\"Failing row contains (e5a624f0-89c9-4776-a6ca-683c94879e1c, 2026-02-01, 000007387 - FERRAGEM MACAGNAN LUSSANI FILHOS LTDA - Material de ..., Geral, -28762.9, 04. SG&A, Real,"
  },
  {
    "batch": 228,
    "status": 400,
    "mensagem": "{\"code\":\"23502\",\"details\":\"Failing row contains (f6902b3e-b9e6-4c5b-8eca-dce7699d22b4, 2026-02-01, 000007387 - FERRAGEM MACAGNAN LUSSANI FILHOS LTDA - Material de ..., Geral, -28762.9, 04. SG&A, Real,"
  },
  {
    "batch": 229,
    "status": 400,
    "mensagem": "{\"code\":\"23502\",\"details\":\"Failing row contains (290dd6e8-6d53-448c-b457-ad1bba6ff10c, 2026-02-01, 000007387 - FERRAGEM MACAGNAN LUSSANI FILHOS LTDA - Material de ..., Geral, -28762.9, 04. SG&A, Real,"
  },
  {
    "batch": 230,
    "status": 400,
    "mensagem": "{\"code\":\"23502\",\"details\":\"Failing row contains (a4f2c865-1f78-47fb-8979-e2912e645848, 2026-02-01, 000007387 - FERRAGEM MACAGNAN LUSSANI FILHOS LTDA - Material de ..., Geral, -28762.9, 04. SG&A, Real,"
  }
]